[
	{
		"id":"1",
		"img":"in-recommend01.jpg",
		"name":"贞操拯救者",
		"exp":"恋爱大师飙车现场!"
	},
	{
		"id":"2",
		"img":"in-recommend02.jpg",
		"name":"妖怪名单（轻读版）",
		"exp":"道家妹子求双修，仙家"
	},
	{
		"id":"3",
		"img":"in-recommend03.jpg",
		"name":"龙符之王道天下",
		"exp":"谁是真龙天子"
	},
	{
		"id":"4",
		"img":"in-recommend04.jpg",
		"name":"拜托别吃我",
		"exp":"这只仓鼠是我的食物"
	},
	{
		"id":"5",
		"img":"in-recommend05.jpg",
		"name":"星武神诀",
		"exp":"一个逆天强者的撼世之"
	},
	{
		"id":"6",
		"img":"in-recommend06.jpg",
		"name":"虚灵",
		"exp":"三年前，暮枫眼看着父 "
	}
]
